astar_art/ART2.py
astar_art/__init__.py
astar_art-0.0.1.dist-info/LICENSE
astar_art-0.0.1.dist-info/METADATA
astar_art-0.0.1.dist-info/WHEEL
astar_art-0.0.1.dist-info/top_level.txt
astar_art-0.0.1.dist-info/RECORD
